crispy_forms_primer/__init__.py
crispy_forms_primer/layout.py
crispy_forms_primer/settings.py
crispy_forms_primer/templates/primer/display_form.html
crispy_forms_primer/templates/primer/errors.html
crispy_forms_primer/templates/primer/errors_formset.html
crispy_forms_primer/templates/primer/field.html
crispy_forms_primer/templates/primer/inputs.html
crispy_forms_primer/templates/primer/messages.html
crispy_forms_primer/templates/primer/multifield.html
crispy_forms_primer/templates/primer/uni_form.html
crispy_forms_primer/templates/primer/whole_uni_form.html
crispy_forms_primer/templates/primer/layout/basebutton.html
crispy_forms_primer/templates/primer/layout/baseinput.html
crispy_forms_primer/templates/primer/layout/checkboxselectmultiple.html
crispy_forms_primer/templates/primer/layout/checkboxselectmultiple_inline.html
crispy_forms_primer/templates/primer/layout/div.html
crispy_forms_primer/templates/primer/layout/dl.html
crispy_forms_primer/templates/primer/layout/field_errors.html
crispy_forms_primer/templates/primer/layout/field_file.html
crispy_forms_primer/templates/primer/layout/help_text.html
crispy_forms_primer/templates/primer/layout/help_text_and_errors.html
crispy_forms_primer/templates/primer/layout/multifield.html
crispy_forms_primer/templates/primer/layout/prepended_appended_text.html
crispy_forms_primer/templates/primer/layout/radioselect.html
crispy_forms_primer/templates/primer/layout/radioselect_inline.html
crispy_forms_primer/templates/primer/pagination/numbered_pagination.html
crispy_forms_primer/templates/primer/pagination/prev_next_pagination.html
crispy_forms_primer/templatetags/__init__.py
crispy_forms_primer/templatetags/primer_forms_field.py
crispy_forms_primer/templatetags/primer_messages.py
crispy_forms_primer/templatetags/primer_pagination.py
crispy_forms_primer-0.4.4.dist-info/LICENSE
crispy_forms_primer-0.4.4.dist-info/METADATA
crispy_forms_primer-0.4.4.dist-info/WHEEL
crispy_forms_primer-0.4.4.dist-info/top_level.txt
crispy_forms_primer-0.4.4.dist-info/zip-safe
crispy_forms_primer-0.4.4.dist-info/RECORD
