Metadata-Version: 2.1
Name: crispy-forms-primer
Version: 0.4.4
Summary: Django application to add 'django-crispy-forms' layout objects for Github Primer
Home-page: https://github.com/galeo/crispy-forms-primer
Author: Yuwei Tian
Author-email: ibluefocus@nospam.outlook.com
License: MIT
Keywords: Django,django-crispy-forms,primer
Platform: UNKNOWN
Classifier: Environment :: Web Environment
Classifier: Framework :: Django
Classifier: Framework :: Django :: 2.2
Classifier: Framework :: Django :: 3.0
Classifier: Framework :: Django :: 3.1
Classifier: Framework :: Django :: 3.2
Classifier: Intended Audience :: Developers
Classifier: License :: OSI Approved :: MIT License
Classifier: Operating System :: OS Independent
Classifier: Programming Language :: Python :: 3
Classifier: Programming Language :: Python :: 3.6
Classifier: Programming Language :: Python :: 3.7
Classifier: Programming Language :: Python :: 3.8
Classifier: Programming Language :: Python :: 3.9
Classifier: Programming Language :: Python :: 3.10
Classifier: Topic :: Internet :: WWW/HTTP
Classifier: Topic :: Internet :: WWW/HTTP :: Dynamic Content
Classifier: Topic :: Software Development :: Libraries :: Python Modules
Requires-Python: >=3.6
License-File: LICENSE
Requires-Dist: Django (>=2.2)
Requires-Dist: django-crispy-forms (>=1.9.0)
